lda2vec/__init__.py
lda2vec/corpus.py
lda2vec/dirichlet_likelihood.py
lda2vec/embed_mixture.py
lda2vec/fake_data.py
lda2vec/lda2vec.py
lda2vec/negative_sampling.py
lda2vec/preprocess.py
lda2vec/topics.py
lda2vec/tracking.py
lda2vec/utils.py
pylda2vec-1.0.0.dist-info/DESCRIPTION.rst
pylda2vec-1.0.0.dist-info/METADATA
pylda2vec-1.0.0.dist-info/RECORD
pylda2vec-1.0.0.dist-info/WHEEL
pylda2vec-1.0.0.dist-info/metadata.json
pylda2vec-1.0.0.dist-info/top_level.txt
tests/__init__.py
