Metadata-Version: 2.0
Name: pylda2vec
Version: 1.0.0
Summary: Mixing Dirichlet Topic Models and Word Embeddings to Make lda2vec
Home-page: https://github.com/ONLPS/lda2vec
Author: ONLPS
Author-email: royalkingpin@gmail.com
Maintainer: ONLPS
Maintainer-email: royalkingpin@gmail.com
License: MIT
Keywords: lda,topic-models,text,text processing,nlp
Platform: UNKNOWN
Classifier: Development Status :: 4 - Beta
Classifier: Intended Audience :: Developers
Classifier: License :: OSI Approved :: MIT License
Classifier: Natural Language :: English
Classifier: Operating System :: OS Independent
Classifier: Programming Language :: Python :: 3.6
Classifier: Programming Language :: Python :: Implementation :: CPython
